warapi/__init__.py
warapi/api/__init__.py
warapi/api/external_api.py
warapi/api/maps_api.py
warapi/api/war_api.py
warapi/api_client.py
warapi/api_response.py
warapi/configuration.py
warapi/exceptions.py
warapi/models/__init__.py
warapi/models/faction_enum.py
warapi/models/map.py
warapi/models/map_item.py
warapi/models/map_text_items.py
warapi/models/server_connection_info.py
warapi/models/shard_status.py
warapi/models/war.py
warapi/models/war_report.py
warapi/py.typed
warapi/rest.py
warapi-1.0.0.dist-info/METADATA
warapi-1.0.0.dist-info/WHEEL
warapi-1.0.0.dist-info/RECORD
